simkl_scrobbler/__init__.py
simkl_scrobbler/backlog_cleaner.py
simkl_scrobbler/cli.py
simkl_scrobbler/compatibility_patches.py
simkl_scrobbler/credentials.py
simkl_scrobbler/main.py
simkl_scrobbler/media_cache.py
simkl_scrobbler/media_tracker.py
simkl_scrobbler/monitor.py
simkl_scrobbler/movie_scrobbler.py
simkl_scrobbler/players/__init__.py
simkl_scrobbler/players/mpc.py
simkl_scrobbler/players/mpv.py
simkl_scrobbler/players/potplayer.py
simkl_scrobbler/players/vlc.py
simkl_scrobbler/service_manager.py
simkl_scrobbler/service_runner.py
simkl_scrobbler/simkl_api.py
simkl_scrobbler/tray_app.py
simkl_scrobbler/utils/__init__.py
simkl_scrobbler/utils/constants.py
simkl_scrobbler/window_detection.py
simkl_scrobbler-1.2.63.dist-info/LICENSE
simkl_scrobbler-1.2.63.dist-info/METADATA
simkl_scrobbler-1.2.63.dist-info/WHEEL
simkl_scrobbler-1.2.63.dist-info/entry_points.txt
simkl_scrobbler-1.2.63.dist-info/RECORD
