Metadata-Version: 2.3
Name: simkl-scrobbler
Version: 1.2.63
Summary: Automatic Movie Scrobbler for Simkl
License: MIT
Keywords: simkl,scrobbler
Author: kavinthangavel
Author-email: kavinthangavel.dev@gmail.com
Requires-Python: >=3.9
Classifier: Development Status :: 4 - Beta
Classifier: Intended Audience :: End Users/Desktop
Classifier: License :: OSI Approved :: MIT License
Classifier: Operating System :: OS Independent
Classifier: Programming Language :: Python :: 3
Classifier: Programming Language :: Python :: 3.9
Classifier: Programming Language :: Python :: 3.10
Classifier: Programming Language :: Python :: 3.11
Classifier: Programming Language :: Python :: 3.12
Classifier: Programming Language :: Python :: 3.13
Provides-Extra: linux
Provides-Extra: macos
Requires-Dist: PyGObject (>=3.42.0) ; (sys_platform == "linux" and python_version >= "3.9" and python_version < "4.0") and (extra == "linux")
Requires-Dist: colorama (>=0.4.4)
Requires-Dist: guessit (>=3.3.0)
Requires-Dist: pillow (>=11.2.0)
Requires-Dist: plyer (>=2.0.0)
Requires-Dist: psutil (>=5.8.0)
Requires-Dist: pygetwindow (>=0.0.9) ; sys_platform == "win32"
Requires-Dist: pyobjc (>=7.3) ; (sys_platform == "darwin") and (extra == "macos")
Requires-Dist: pystray (>=0.19.0)
Requires-Dist: python-dotenv (>=0.15.0)
Requires-Dist: python-xlib (>=0.31) ; (sys_platform == "linux") and (extra == "linux")
Requires-Dist: pywin32 (>=300) ; sys_platform == "win32"
Requires-Dist: requests (>=2.25.0)
Project-URL: Homepage, https://github.com/kavinthangavel/simkl-scrobbler
Project-URL: Repository, https://github.com/kavinthangavel/simkl-scrobbler
